marcador/__init__.py
marcador/__main__.py
marcador/bookmarkimporter.py
marcador/bottle.py
marcador/json_backend.py
marcador/lib.py
marcador/marcador_test.py
marcador/proxy.py
marcador/rofi.py
marcador/rofi_marcador.py
marcador/server.py
marcador/version.py
marcador-0.5.2.dist-info/LICENSE.txt
marcador-0.5.2.dist-info/METADATA
marcador-0.5.2.dist-info/WHEEL
marcador-0.5.2.dist-info/entry_points.txt
marcador-0.5.2.dist-info/top_level.txt
marcador-0.5.2.dist-info/RECORD
